CONTRIBUTORS.txt
COPYRIGHT.txt
LICENSES.txt
MANIFEST.in
README.md
README.txt
TODO.txt
setup.cfg
setup.py
tox.ini
docs/Makefile
docs/api.rst
docs/conf.py
docs/configuration.rst
docs/development.rst
docs/events.rst
docs/faq.rst
docs/glossary.rst
docs/index.rst
docs/installing.rst
docs/introduction.rst
docs/logging.rst
docs/plugins.rst
docs/running.rst
docs/subprocess-transitions.png
docs/subprocess.rst
docs/upgrading.rst
docs/xmlrpc.rst
docs/.static/logo_hi.gif
docs/.static/repoze.css
supervisor/__init__.py
supervisor/childutils.py
supervisor/compat.py
supervisor/confecho.py
supervisor/datatypes.py
supervisor/dispatchers.py
supervisor/events.py
supervisor/http.py
supervisor/http_client.py
supervisor/loggers.py
supervisor/options.py
supervisor/pidproxy.py
supervisor/poller.py
supervisor/process.py
supervisor/rpcinterface.py
supervisor/socket_manager.py
supervisor/states.py
supervisor/supervisorctl.py
supervisor/supervisord.py
supervisor/version.txt
supervisor/web.py
supervisor/xmlrpc.py
supervisor/medusa/__init__.py
supervisor/medusa/asynchat_25.py
supervisor/medusa/asyncore_25.py
supervisor/medusa/auth_handler.py
supervisor/medusa/counter.py
supervisor/medusa/default_handler.py
supervisor/medusa/filesys.py
supervisor/medusa/http_date.py
supervisor/medusa/http_server.py
supervisor/medusa/logger.py
supervisor/medusa/producers.py
supervisor/medusa/text_socket.py
supervisor/medusa/util.py
supervisor/medusa/xmlrpc_handler.py
supervisor/scripts/loop_eventgen.py
supervisor/scripts/loop_listener.py
supervisor/scripts/sample_commevent.py
supervisor/scripts/sample_eventlistener.py
supervisor/scripts/sample_exiting_eventlistener.py
supervisor/skel/sample.conf
supervisor/tests/__init__.py
supervisor/tests/base.py
supervisor/tests/test_childutils.py
supervisor/tests/test_confecho.py
supervisor/tests/test_datatypes.py
supervisor/tests/test_dispatchers.py
supervisor/tests/test_events.py
supervisor/tests/test_http.py
supervisor/tests/test_http_client.py
supervisor_plus_cron.egg-info/PKG-INFO
supervisor_plus_cron.egg-info/SOURCES.txt
supervisor_plus_cron.egg-info/dependency_links.txt
supervisor_plus_cron.egg-info/entry_points.txt
supervisor_plus_cron.egg-info/not-zip-safe
supervisor_plus_cron.egg-info/requires.txt
supervisor_plus_cron.egg-info/top_level.txt