Metadata-Version: 1.1
Name: supervisor-plus-cron
Version: 1.0.15201
Summary: From 4.0.0.dev0: A system for controlling process state under UNIX, plus CRON!
Home-page: https://github.com/klahnakoski/supervisor-plus-cron
Author: Kyle Lahnakoski
Author-email: kyle@lahnakoski.com
License: BSD-derived (http://www.repoze.org/LICENSE.txt)
Platform: UNKNOWN
Classifier: Development Status :: 4 - Beta
Classifier: Environment :: No Input/Output (Daemon)
Classifier: Intended Audience :: System Administrators
Classifier: Natural Language :: English
Classifier: Operating System :: POSIX
Classifier: Topic :: System :: Boot
Classifier: Topic :: System :: Monitoring
Classifier: Topic :: System :: Systems Administration
Classifier: Programming Language :: Python
Classifier: Programming Language :: Python :: 2
Classifier: Programming Language :: Python :: 2.6
Classifier: Programming Language :: Python :: 2.7
Classifier: Programming Language :: Python :: 3
Classifier: Programming Language :: Python :: 3.2
Classifier: Programming Language :: Python :: 3.3
Classifier: Programming Language :: Python :: 3.4
